<annotation>
	<folder>images</folder>
	<filename>Plate725.png</filename>
	<path>F:\Visual-Studio Projekte\Eigener Datensatz\object_detection_demo-master\data\images\Plate725.png</path>
	<source>
		<database>Unknown</database>
	</source>
	<size>
		<width>400</width>
		<height>267</height>
		<depth>3</depth>
	</size>
	<segmented>0</segmented>
	<object>
		<name>Plate</name>
		<pose>Unspecified</pose>
		<truncated>0</truncated>
		<difficult>0</difficult>
		<bndbox>
			<xmin>83</xmin>
			<ymin>214</ymin>
			<xmax>140</xmax>
			<ymax>233</ymax>
		</bndbox>
	</object>
	<object>
		<name>Plate</name>
		<pose>Unspecified</pose>
		<truncated>0</truncated>
		<difficult>0</difficult>
		<bndbox>
			<xmin>312</xmin>
			<ymin>130</ymin>
			<xmax>361</xmax>
			<ymax>142</ymax>
		</bndbox>
	</object>
</annotation>
