<annotation>
	<folder>images</folder>
	<filename>Plate531.png</filename>
	<path>F:\Visual-Studio Projekte\Eigener Datensatz\object_detection_demo-master\data\images\Plate531.png</path>
	<source>
		<database>Unknown</database>
	</source>
	<size>
		<width>800</width>
		<height>450</height>
		<depth>3</depth>
	</size>
	<segmented>0</segmented>
	<object>
		<name>Plate</name>
		<pose>Unspecified</pose>
		<truncated>0</truncated>
		<difficult>0</difficult>
		<bndbox>
			<xmin>198</xmin>
			<ymin>236</ymin>
			<xmax>229</xmax>
			<ymax>247</ymax>
		</bndbox>
	</object>
</annotation>
